miranda/__init__.py
miranda/cv.py
miranda/scripting.py
miranda/storage.py
miranda/units.py
miranda/utils.py
miranda/convert/__init__.py
miranda/convert/_aggregation.py
miranda/convert/_data_corrections.py
miranda/convert/_data_definitions.py
miranda/convert/_reconstruction.py
miranda/convert/corrections.py
miranda/convert/deh.py
miranda/convert/eccc_canswe.py
miranda/convert/eccc_rdrs.py
miranda/convert/hq.py
miranda/convert/melcc.py
miranda/convert/stationdata.py
miranda/convert/utils.py
miranda/convert/data/cmip_ouranos_attrs.json
miranda/convert/data/deh_cf_attrs.json
miranda/convert/data/eccc-canhomt_Temp_Stations_Gen4_2024_monthly.zip
miranda/convert/data/eccc-canhomt_cf_attrs.json
miranda/convert/data/eccc_ahccd_cf_attrs.json
miranda/convert/data/eccc_canswe_cf_attrs.json
miranda/convert/data/eccc_casr_cf_attrs.json
miranda/convert/data/eccc_obs_cf_attrs.json
miranda/convert/data/eccc_rdrs_cf_attrs.json
miranda/convert/data/ecmwf_cf_attrs.json
miranda/convert/data/emdna_cf_attrs.json
miranda/convert/data/espo-g6-e5l_attrs.json
miranda/convert/data/espo-g6-r2_attrs.json
miranda/convert/data/ets_grnch_cf_attrs.json
miranda/convert/data/ghcn-countries.txt.zip
miranda/convert/data/ghcnd-stations.txt.zip
miranda/convert/data/ghcnd_cf_attrs.json
miranda/convert/data/ghcnh-station-list.txt.zip
miranda/convert/data/ghcnh_cf_attrs.json
miranda/convert/data/hq_cf_attrs.json
miranda/convert/data/melcc_cf_attrs.json
miranda/convert/data/nasa_cf_attrs.json
miranda/convert/data/nex-gddp-cmip6_attrs.json
miranda/convert/data/nrcan_gridded_obs_cf_attrs.json
miranda/convert/data/ouranos_orrc_cf_attrs.json
miranda/convert/data/rvt_raven_attrs.json
miranda/convert/data/timezones-with-oceans-now.shapefile.zip
miranda/convert/data/usask_cf_attrs.json
miranda/decode/__init__.py
miranda/decode/_decoder.py
miranda/decode/_time.py
miranda/eccc/__init__.py
miranda/eccc/_homogenized.py
miranda/eccc/_raw.py
miranda/eccc/_support_rvt.py
miranda/eccc/_utils.py
miranda/eccc/geomet.py
miranda-0.6.0.dist-info/licenses/LICENSE
miranda-0.6.0.dist-info/WHEEL
miranda-0.6.0.dist-info/METADATA
miranda-0.6.0.dist-info/RECORD
