Metadata-Version: 2.4
Name: miranda
Version: 0.6.0
Summary: Python utilities for climate data collection, conversion, and management.
Keywords: xarray,climate,meteorology,hydrology,archiving,collection,conversion,miranda
Author-email: Trevor James Smith <smith.trevorj@ouranos.ca>
Maintainer-email: Trevor James Smith <smith.trevorj@ouranos.ca>, Travis Logan <logan.travis@ouranos.ca>, Pascal Bourgault <bourgault.pascal@ouranos.ca>
Requires-Python: >=3.10.0
Classifier: Development Status :: 3 - Alpha
Classifier: Intended Audience :: Developers
Classifier: Intended Audience :: Science/Research
Classifier: License :: OSI Approved :: Apache Software License
Classifier: Natural Language :: English
Classifier: Operating System :: OS Independent
Classifier: Programming Language :: Python :: 3
Classifier: Programming Language :: Python :: 3.10
Classifier: Programming Language :: Python :: 3.11
Classifier: Programming Language :: Python :: 3.12
Classifier: Programming Language :: Python :: 3.13
Classifier: Programming Language :: Python :: Implementation :: CPython
Classifier: Topic :: Scientific/Engineering :: Atmospheric Science
Classifier: Typing :: Typed
License-File: LICENSE
Requires-Dist: cftime
Requires-Dist: cf-xarray >=0.10.4
Requires-Dist: dask >=2024.8.1
Requires-Dist: distributed
Requires-Dist: h5netcdf
Requires-Dist: netCDF4 >=1.6.4
Requires-Dist: numcodecs <0.16
Requires-Dist: numpy >=1.25
Requires-Dist: pandas
Requires-Dist: pyessv
Requires-Dist: pyyaml
Requires-Dist: schema
Requires-Dist: xarray >=2023.11.0
Requires-Dist: xclim >=0.57.0
Requires-Dist: zarr
Requires-Dist: miranda[dev] ; extra == "all"
Requires-Dist: miranda[docs] ; extra == "all"
Requires-Dist: miranda[gis] ; extra == "all"
Requires-Dist: miranda[remote] ; extra == "all"
Requires-Dist: bump-my-version >=0.28.0 ; extra == "dev"
Requires-Dist: coverage >=7.5.0 ; extra == "dev"
Requires-Dist: flake8 >=7.2.0 ; extra == "dev"
Requires-Dist: flake8-rst-docstrings >=0.3.0 ; extra == "dev"
Requires-Dist: flit >=3.11.0,<4.0 ; extra == "dev"
Requires-Dist: mypy >=1.14.1 ; extra == "dev"
Requires-Dist: numpydoc >=1.8.0 ; extra == "dev"
Requires-Dist: pooch >=1.8.0 ; extra == "dev"
Requires-Dist: pip >=25.1.1 ; extra == "dev"
Requires-Dist: pooch >=1.8.0 ; extra == "dev"
Requires-Dist: pre-commit >=3.5.0 ; extra == "dev"
Requires-Dist: pytest >=8.3.2 ; extra == "dev"
Requires-Dist: pytest-cov >=5.0.0 ; extra == "dev"
Requires-Dist: pytest-xdist >=3.2.0 ; extra == "dev"
Requires-Dist: ruff >=0.12.0 ; extra == "dev"
Requires-Dist: tox >=4.26.0 ; extra == "dev"
Requires-Dist: watchdog >=4.0.0 ; extra == "dev"
Requires-Dist: furo >=2023.07.26 ; extra == "docs"
Requires-Dist: ipykernel ; extra == "docs"
Requires-Dist: ipython ; extra == "docs"
Requires-Dist: jupyter_client ; extra == "docs"
Requires-Dist: nbsphinx >=0.9.5 ; extra == "docs"
Requires-Dist: sphinx >=7.1.0,<8.2.0 ; extra == "docs"
Requires-Dist: sphinx-intl ; extra == "docs"
Requires-Dist: sphinx-mdinclude ; extra == "docs"
Requires-Dist: sphinx_codeautolink >=0.16.2 ; extra == "docs"
Requires-Dist: sphinx_copybutton ; extra == "docs"
Requires-Dist: clisops >=0.16.1 ; extra == "gis"
Requires-Dist: geopandas >=1.0.0 ; extra == "gis"
Requires-Dist: regionmask >=0.13.0 ; extra == "gis"
Requires-Dist: shapely >=2.0 ; extra == "gis"
Requires-Dist: xesmf ; extra == "gis"
Requires-Dist: cdsapi ; extra == "remote"
Requires-Dist: ecmwf-api-client ; extra == "remote"
Requires-Dist: intake ; extra == "remote"
Requires-Dist: intake-esm ; extra == "remote"
Requires-Dist: requests >=2.31 ; extra == "remote"
Requires-Dist: s3fs ; extra == "remote"
Project-URL: About Ouranos, https://ouranos.ca/en/
Project-URL: Changelog, https://miranda.readthedocs.io/en/stable/changelog.html
Project-URL: Homepage, https://miranda.readthedocs.io/
Project-URL: Issue tracker, https://github.com/Ouranosinc/miranda/issues
Project-URL: Source, https://github.com/Ouranosinc/miranda/
Provides-Extra: all
Provides-Extra: dev
Provides-Extra: docs
Provides-Extra: gis
Provides-Extra: remote
